llama_index/storage/kvstore/firestore/__init__.py
llama_index/storage/kvstore/firestore/base.py
flying_delta_storage_kvstore_firestore-0.1.0.dist-info/METADATA
flying_delta_storage_kvstore_firestore-0.1.0.dist-info/WHEEL
flying_delta_storage_kvstore_firestore-0.1.0.dist-info/RECORD
